Workbook

Sheet Transactions
A1: Date | B1: Description | C1: Category | D1: Type | E1: Amount
A2: 46113 | B2: Lunch | C2: Food | D2: Expense | E2: 120
A3: 46114 | B3: Bus | C3: Travel | D3: Expense | E3: 50
A4: 46115 | B4: Salary | C4: Income | D4: Income | E4: 15000
A5: 46116 | B5: Groceries | C5: Food | D5: Expense | E5: 800
A6: 46117 | B6: Movie | C6: Entertainment | D6: Expense | E6: 300
A7: 46118 | B7: Freelance | C7: Income | D7: Income | E7: 2000
A8: 46119 | B8: Shopping | C8: Shopping | D8: Expense | E8: 1200
A9: 46120 | B9: Rent | C9: Rent | D9: Expense | E9: 5000
A10: 46121 | B10: Electricity | C10: Bills | D10: Expense | E10: 900
A11: 46122 | B11: Snacks | C11: Food | D11: Expense | E11: 150
A12: 46123 | B12: Uber | C12: Travel | D12: Expense | E12: 220
A13: 46124 | B13: Coffee | C13: Food | D13: Expense | E13: 180
... A31: 46142 | B31: Freelance | C31: Income | D31: Income | E31: 2500

Sheet summary
A1: Metric | B1: Value
A2: Total Income | B2: =SUMIF(Transactions!D:D,"Income",Transactions!E:E) -> 26500
A3: Total Expense | B3: =SUMIF(Transactions!D:D,"Expense",Transactions!E:E) -> 18860
A4: Net Balance | B4: =B2-B3 -> 7640
A5: Average Expense | B5: =AVERAGEIF(Transactions!D:D,"Expense",Transactions!E:E) -> 754.4
A6: Total Transactions | B6: =COUNTA(Transactions!A:A)-1 -> 30
A7: Highest Expense | B7: =_xlfn.MAXIFS(Transactions!E:E,Transactions!D:D,"Expense") -> 5000
A8: Lowest Expense | B8: =_xlfn.MINIFS(Transactions!E:E,Transactions!D:D,"Expense") -> 50
A9: Savings % | B9: =(B2-B3)/B2 -> 0.28830189

Sheet budget
A1: Category | B1: Budget | C1: Actual | D1: Difference | E1: Status
A2: Food | B2: =VLOOKUP(A2,lookup!A:B,2,FALSE) -> 4000 | C2: =SUMIF(Transactions!C:C,A2,Transactions!E:E) -> 3350 | D2: =B2-C2 -> 650 | E2: =IF(C2>B2,"Over","OK") -> OK
A3: Travel | B3: =VLOOKUP(A3,lookup!A:B,2,FALSE) -> 2000 | C3: =SUMIF(Transactions!C:C,A3,Transactions!E:E) -> 1010 | D3: =B3-C3 -> 990 | E3: =IF(C3>B3,"Over","OK") -> OK
A4: Shopping | B4: =VLOOKUP(A4,lookup!A:B,2,FALSE) -> 4000 | C4: =SUMIF(Transactions!C:C,A4,Transactions!E:E) -> 6400 | D4: =B4-C4 -> -2400 | E4: =IF(C4>B4,"Over","OK") -> Over
A5: Rent | B5: =VLOOKUP(A5,lookup!A:B,2,FALSE) -> 6000 | C5: =SUMIF(Transactions!C:C,A5,Transactions!E:E) -> 5000 | D5: =B5-C5 -> 1000 | E5: =IF(C5>B5,"Over","OK") -> OK
A6: Bills | B6: =VLOOKUP(A6,lookup!A:B,2,FALSE) -> 3000 | C6: =SUMIF(Transactions!C:C,A6,Transactions!E:E) -> 2400 | D6: =B6-C6 -> 600 | E6: =IF(C6>B6,"Over","OK") -> OK
A7: Entertainment | B7: =VLOOKUP(A7,lookup!A:B,2,FALSE) -> 2000 | C7: =SUMIF(Transactions!C:C,A7,Transactions!E:E) -> 700 | D7: =B7-C7 -> 1300 | E7: =IF(C7>B7,"Over","OK") -> OK

Sheet extra quiries
A1: Query | B1: Result
A2: Food Expense | B2: =SUMIF(Transactions!C:C,"Food",Transactions!E:E) -> 3350
A3: Travel Expense | B3: =SUMIF(Transactions!C:C,"Travel",Transactions!E:E) -> 1010
A4: Shopping Expense | B4: =SUMIF(Transactions!C:C,"Shopping",Transactions!E:E) -> 6400
A5: Income Total | B5: =SUMIF(Transactions!D:D,"Income",Transactions!E:E) -> 26500
A6: Expense Total | B6: =SUMIF(Transactions!D:D,"Expense",Transactions!E:E) -> 18860
A7: Savings % | B7: =(summary!B2-summary!B3)/summary!B2 -> 0.28830189
A8: Top Expense | B8: =MAX(Transactions!E:E) -> 15000
A9: Min Expense | B9: =MIN(Transactions!E:E) -> 50
A10: Transaction Count | B10: =COUNTA(Transactions!A:A)-1 -> 30
A11: Food Transactions | B11: =COUNTIF(Transactions!C:C,"Food") -> 9
A12: Expense Days | B12: =COUNTIF(Transactions!D:D,"Expense") -> 25
A13: Income Days | B13: =COUNTIF(Transactions!D:D,"Income") -> 5
A14: Average Expense | B14: =AVERAGEIF(Transactions!D:D,"Expense",Transactions!E:E) -> 754.4
A15: Total Rent | B15: =SUMIF(Transactions!C:C,"Rent",Transactions!E:E) -> 5000
A16: Total Bills | B16: =SUMIF(Transactions!C:C,"Bills",Transactions!E:E) -> 2400
A17: April Income | B17: =HLOOKUP("Income",lookup!A10:E12,5,FALSE) -> #N/A

Sheet lookup
A1: Category | B1: Limit
A2: Food | B2: 4000
A3: Travel | B3: 2000
A4: Shopping | B4: 4000
A5: Rent | B5: 6000
A6: Bills | B6: 3000
A7: Entertainment | B7: 2000
A10: Type | B10: Jan | C10: Feb | D10: Mar | E10: Apr
A11: Income | B11: 20000 | C11: 22000 | D11: 24000 | E11: 26000
A12: Expense | B12: 15000 | C12: 16000 | D12: 18000 | E12: 20000
